PyVizyal/__init__.py
PyVizyal-1.5.dist-info/METADATA
PyVizyal-1.5.dist-info/WHEEL
PyVizyal-1.5.dist-info/top_level.txt
PyVizyal-1.5.dist-info/RECORD
