Metadata-Version: 2.1
Name: PyVizyal
Version: 1.5
Summary: Frame Update!!
Author: SGG
Author-email: dtumanov446@gmail.com
Classifier: Programming Language :: Python :: 3
Classifier: License :: OSI Approved :: MIT License
Classifier: Operating System :: OS Independent
Requires-Python: >=3.6
